LICENSE
MANIFEST.in
README.rst
setup.py
caerbannog/__init__.py
caerbannog.egg-info/PKG-INFO
caerbannog.egg-info/SOURCES.txt
caerbannog.egg-info/dependency_links.txt
caerbannog.egg-info/not-zip-safe
caerbannog.egg-info/top_level.txt