Metadata-Version: 1.0
Name: caerbannog
Version: 0.1
Summary: High-level interface to Vowpal Wabbit
Home-page: http://github.com/ztane/caerbannog
Author: Antti Haapala
Author-email: antti.haapala@anttipatterns.com
License: MIT
Platform: UNKNOWN
